sev_attest_tool-0.2.4.dist-info/METADATA
sev_attest_tool-0.2.4.dist-info/WHEEL
sev_attest_tool/__init__.py
sev_attest_tool/sev_attest_tool.pypy310-pp73-x86_64-linux-gnu.so
sev_attest_tool-0.2.4.dist-info/RECORD
