Metadata-Version: 2.1
Name: sev_attest_tool
Version: 0.2.4
Classifier: Programming Language :: Rust
Classifier: Programming Language :: Python :: Implementation :: CPython
Classifier: Programming Language :: Python :: Implementation :: PyPy
Summary: Rust implementation of SEV-SNP attestation verification
Keywords: sev-snp,sev,amd,attestation,cryptography
Home-Page: https://blyss.dev
Author: Samir Menon <samir@blyss.dev>, Neil Movva <neil@blyss.dev>
Author-email: Samir Menon <samir@blyss.dev>, Neil Movva <neil@blyss.dev>
License: MIT
Requires-Python: >=3.8
